odoo_openupgrade_wizard/__init__.py
odoo_openupgrade_wizard/__main__.py
odoo_openupgrade_wizard/cli/cli.py
odoo_openupgrade_wizard/cli/cli_copydb.py
odoo_openupgrade_wizard/cli/cli_docker_build.py
odoo_openupgrade_wizard/cli/cli_dropdb.py
odoo_openupgrade_wizard/cli/cli_dumpdb.py
odoo_openupgrade_wizard/cli/cli_estimate_workload.py
odoo_openupgrade_wizard/cli/cli_execute_script_python.py
odoo_openupgrade_wizard/cli/cli_execute_script_sql.py
odoo_openupgrade_wizard/cli/cli_generate_module_analysis.py
odoo_openupgrade_wizard/cli/cli_get_code.py
odoo_openupgrade_wizard/cli/cli_guess_requirement.py
odoo_openupgrade_wizard/cli/cli_init.py
odoo_openupgrade_wizard/cli/cli_install_from_csv.py
odoo_openupgrade_wizard/cli/cli_options.py
odoo_openupgrade_wizard/cli/cli_psql.py
odoo_openupgrade_wizard/cli/cli_pull_submodule.py
odoo_openupgrade_wizard/cli/cli_restoredb.py
odoo_openupgrade_wizard/cli/cli_run.py
odoo_openupgrade_wizard/cli/cli_upgrade.py
odoo_openupgrade_wizard/configuration_version_dependant.py
odoo_openupgrade_wizard/templates/.gitignore.j2
odoo_openupgrade_wizard/templates/analysis.html.j2
odoo_openupgrade_wizard/templates/config.yml.j2
odoo_openupgrade_wizard/templates/custom-postgres.conf.j2
odoo_openupgrade_wizard/templates/modules.csv.j2
odoo_openupgrade_wizard/templates/odoo/11.0/Dockerfile
odoo_openupgrade_wizard/templates/odoo/12.0/Dockerfile
odoo_openupgrade_wizard/templates/odoo/13.0/Dockerfile
odoo_openupgrade_wizard/templates/odoo/14.0/Dockerfile
odoo_openupgrade_wizard/templates/odoo/15.0/Dockerfile
odoo_openupgrade_wizard/templates/odoo/16.0/Dockerfile
odoo_openupgrade_wizard/templates/odoo/17.0/Dockerfile
odoo_openupgrade_wizard/templates/odoo/18.0/Dockerfile
odoo_openupgrade_wizard/templates/odoo/addons_debian_requirements.txt.j2
odoo_openupgrade_wizard/templates/odoo/addons_python_requirements.txt.j2
odoo_openupgrade_wizard/templates/odoo/extra_debian_requirements.txt.j2
odoo_openupgrade_wizard/templates/odoo/extra_python_requirements.txt.j2
odoo_openupgrade_wizard-1.3.1.dist-info/METADATA
odoo_openupgrade_wizard-1.3.1.dist-info/WHEEL
odoo_openupgrade_wizard-1.3.1.dist-info/entry_points.txt
odoo_openupgrade_wizard-1.3.1.dist-info/RECORD
