Metadata-Version: 2.4
Name: odoo-openupgrade-wizard
Version: 1.3.1
Summary: CLI tool to manage Odoo Major Upgrades
Keywords: cli,odoo,openupgrade
Author: Sylvain LE GAL
Author-email: sylvain.legal@grap.coop
Maintainer: Sylvain LE GAL
Maintainer-email: sylvain.legal@grap.coop
Requires-Python: >=3.9,<4.0
Classifier: License :: OSI Approved :: GNU Affero General Public License v3 or later (AGPLv3+)
Classifier: Intended Audience :: Developers
Classifier: Development Status :: 4 - Beta
Classifier: Operating System :: Unix
Classifier: Programming Language :: Python :: 3.9
Classifier: Programming Language :: Python :: 3.10
Classifier: Programming Language :: Python :: 3.11
Classifier: Programming Language :: Python :: 3.12
Classifier: Framework :: Odoo
Requires-Dist: GitPython (>=3.1,<4.0)
Requires-Dist: click (>=7.0,<8.0)
Requires-Dist: click-loglevel (>=0.4)
Requires-Dist: docker (>=7.0,<8.0)
Requires-Dist: git-aggregator (>=2.1,<3.0)
Requires-Dist: importlib-resources (>=5.4,<6.0)
Requires-Dist: jinja2 (>=3.0,<4.0)
Requires-Dist: loguru (>=0.6)
Requires-Dist: odoorpc (>=0.10.1)
Requires-Dist: plumbum (>=1.7,<2.0)
Requires-Dist: pygount (>=1.4,<2.0)
Requires-Dist: pyyaml (>=6.0.0,<7.0.0)
Requires-Dist: single-source (>=0.3)
Project-URL: Repository, https://gitlab.com/odoo-openupgrade-wizard/odoo-openupgrade-wizard
